LICENSE
MANIFEST.in
README.md
setup.py
drf_form_bootstrap_4.egg-info/PKG-INFO
drf_form_bootstrap_4.egg-info/SOURCES.txt
drf_form_bootstrap_4.egg-info/dependency_links.txt
drf_form_bootstrap_4.egg-info/not-zip-safe
drf_form_bootstrap_4.egg-info/requires.txt
drf_form_bootstrap_4.egg-info/top_level.txt
drfformbootstrap4/__init__.py
drfformbootstrap4/apps.py
drfformbootstrap4/forms.py
drfformbootstrap4/serializers.py
drfformbootstrap4/tests.py
drfformbootstrap4/urls.py
drfformbootstrap4/views.py
drfformbootstrap4/templates/drfformbootstrap4/checkbox.html
drfformbootstrap4/templates/drfformbootstrap4/checkbox_multiple.html
drfformbootstrap4/templates/drfformbootstrap4/error_text.html
drfformbootstrap4/templates/drfformbootstrap4/form_errors.html
drfformbootstrap4/templates/drfformbootstrap4/help_text.html
drfformbootstrap4/templates/drfformbootstrap4/input.html
drfformbootstrap4/templates/drfformbootstrap4/label.html
drfformbootstrap4/templates/drfformbootstrap4/legend.html
drfformbootstrap4/templates/drfformbootstrap4/radio.html
drfformbootstrap4/templates/drfformbootstrap4/select.html
drfformbootstrap4/templates/drfformbootstrap4/select_multiple.html
drfformbootstrap4/templates/drfformbootstrap4/textarea.html
drfformbootstrap4/templates/drfformbootstrap4/demo/base.html
drfformbootstrap4/templates/drfformbootstrap4/demo/horizontal.html
drfformbootstrap4/templates/drfformbootstrap4/demo/inline.html
drfformbootstrap4/templates/drfformbootstrap4/demo/root.html
drfformbootstrap4/templates/drfformbootstrap4/demo/vertical.html
drfformbootstrap4/templates/drfformbootstrap4/horizontal/checkbox.html
drfformbootstrap4/templates/drfformbootstrap4/horizontal/checkbox_multiple.html
drfformbootstrap4/templates/drfformbootstrap4/horizontal/dict_field.html
drfformbootstrap4/templates/drfformbootstrap4/horizontal/fieldset.html
drfformbootstrap4/templates/drfformbootstrap4/horizontal/form.html
drfformbootstrap4/templates/drfformbootstrap4/horizontal/input.html
drfformbootstrap4/templates/drfformbootstrap4/horizontal/list_field.html
drfformbootstrap4/templates/drfformbootstrap4/horizontal/list_fieldset.html
drfformbootstrap4/templates/drfformbootstrap4/horizontal/radio.html
drfformbootstrap4/templates/drfformbootstrap4/horizontal/select.html
