Metadata-Version: 2.1
Name: drf-form-bootstrap-4
Version: 0.5.2
Summary: Bootstrap 4 templates for Django Rest Framework `render_form` tag
Home-page: https://github.com/mattfox/drf-form-bootstrap-4
Author: Matt Fox
Author-email: matt@tansen.ca
License: MIT
Platform: UNKNOWN
